{
    "simple-web-app": [
      {
        "PutRequest": {
          "Item":
          {
            "Timestamp": {
              "S": "freeCodeCamp"
            },
            "Comments": {
              "S": "https://github.com/freeCodeCamp/freeCodeCamp"
            }
          }
        }
      },
      {
        "PutRequest": {
          "Item":
          {
            "Timestamp": {
              "S": "trending"
            },
            "Comments": {
              "S": "https://github.com/trending"
            }
          }
        }
      }
    ]
  }